fteikpy/__about__.py
fteikpy/__init__.py
fteikpy/_base.py
fteikpy/_common.py
fteikpy/_grid.py
fteikpy/_helpers.py
fteikpy/_io.py
fteikpy/_solver.py
fteikpy/_fteik/__init__.py
fteikpy/_fteik/_common.py
fteikpy/_fteik/_fteik2d.py
fteikpy/_fteik/_fteik3d.py
fteikpy/_fteik/_ray2d.py
fteikpy/_fteik/_ray3d.py
fteikpy/_interp/__init__.py
fteikpy/_interp/_interp2d.py
fteikpy/_interp/_interp3d.py
fteikpy/_interp/_vinterp2d.py
fteikpy/_interp/_vinterp3d.py
fteikpy-2.4.0.dist-info/LICENSE
fteikpy-2.4.0.dist-info/METADATA
fteikpy-2.4.0.dist-info/WHEEL
fteikpy-2.4.0.dist-info/top_level.txt
fteikpy-2.4.0.dist-info/RECORD
