Metadata-Version: 2.1
Name: fteikpy
Version: 2.4.0
Summary: Accurate Eikonal solver for Python
Home-page: https://github.com/keurfonluu/fteikpy
Author: Keurfon Luu
License: BSD 3-Clause License
Project-URL: Code, https://github.com/keurfonluu/fteikpy
Project-URL: Issues, https://github.com/keurfonluu/fteikpy/issues
Platform: any
Classifier: License :: OSI Approved :: BSD License
Classifier: Operating System :: OS Independent
Classifier: Development Status :: 5 - Production/Stable
Classifier: Programming Language :: Python :: 3.6
Classifier: Programming Language :: Python :: 3.7
Classifier: Programming Language :: Python :: 3.8
Classifier: Programming Language :: Python :: 3.9
Classifier: Programming Language :: Python :: 3.10
Classifier: Natural Language :: English
Classifier: Intended Audience :: Science/Research
Classifier: Topic :: Scientific/Engineering
Classifier: Topic :: Scientific/Engineering :: Physics
Requires-Python: >=3.6
License-File: LICENSE
Requires-Dist: importlib-metadata
Requires-Dist: numpy
Requires-Dist: numba
Provides-Extra: full
Requires-Dist: scipy ; extra == 'full'
Requires-Dist: meshio (>=4.0) ; extra == 'full'
